<?xml version="1.0" encoding="UTF-8" ?>
<root>
  <node>
    <id>0</id>
    <exec_a>0</exec_a>
    <exec_b>0</exec_b>
    <childs>1</childs>
    <vtx_read/>
    <vtx_write/>
  </node>
  <node>
    <id>1</id>
    <exec_a>20</exec_a>
    <exec_b>5</exec_b>
    <childs>2</childs>
    <vtx_read/>
    <vtx_write>0</vtx_write>
  </node>
  <node>
    <id>2</id>
    <exec_a>30</exec_a>
    <exec_b>1500</exec_b>
    <childs>3</childs>
    <vtx_read/>
    <vtx_write>0</vtx_write>
  </node>
  <node>
    <id>3</id>
    <exec_a>100</exec_a>
    <exec_b>25</exec_b>
    <childs>4</childs>
    <vtx_read/>
    <vtx_write>1</vtx_write>
  </node>
  <node>
    <id>4</id>
    <exec_a>20</exec_a>
    <exec_b>5</exec_b>
    <childs>5</childs>
    <vtx_read/>
    <vtx_write>2</vtx_write>
  </node>
  <node>
    <id>5</id>
    <exec_a>10</exec_a>
    <exec_b>7</exec_b>
    <childs>6</childs>
    <vtx_read/>
    <vtx_write>2</vtx_write>
  </node>
  <node>
    <id>6</id>
    <exec_a>40</exec_a>
    <exec_b>25</exec_b>
    <childs>7</childs>
    <childs>17</childs>
    <vtx_read>0</vtx_read>
    <vtx_read>2</vtx_read>
    <vtx_write/>
  </node>
  <node>
    <id>7</id>
    <exec_a>20</exec_a>
    <exec_b>5</exec_b>
    <childs>8</childs>
    <vtx_read/>
    <vtx_write>3</vtx_write>
  </node>
  <node>
    <id>8</id>
    <exec_a>20</exec_a>
    <exec_b>5</exec_b>
    <childs>9</childs>
    <vtx_read/>
    <vtx_write>3</vtx_write>
  </node>
  <node>
    <id>9</id>
    <exec_a>75</exec_a>
    <exec_b>60</exec_b>
    <childs>10</childs>
    <childs>16</childs>
    <vtx_read>0</vtx_read>
    <vtx_read>2</vtx_read>
    <vtx_read>3</vtx_read>
    <vtx_write/>
  </node>
  <node>
    <id>10</id>
    <exec_a>90</exec_a>
    <exec_b>60</exec_b>
    <childs>11</childs>
    <childs>15</childs>
    <vtx_read>1</vtx_read>
    <vtx_read>3</vtx_read>
    <vtx_write/>
  </node>
  <node>
    <id>11</id>
    <exec_a>20</exec_a>
    <exec_b>5</exec_b>
    <childs>12</childs>
    <vtx_read/>
    <vtx_write>4</vtx_write>
  </node>
  <node>
    <id>12</id>
    <exec_a>30</exec_a>
    <exec_b>20</exec_b>
    <childs>13</childs>
    <vtx_read>1</vtx_read>
    <vtx_read>3</vtx_read>
    <vtx_write>4</vtx_write>
  </node>
  <node>
    <id>13</id>
    <exec_a>40</exec_a>
    <exec_b>25</exec_b>
    <childs>14</childs>
    <vtx_read/>
    <vtx_write>1</vtx_write>
    <vtx_write>3</vtx_write>
  </node>
  <node>
    <id>14</id>
    <exec_a>30</exec_a>
    <exec_b>20</exec_b>
    <childs>15</childs>
    <vtx_read>4</vtx_read>
    <vtx_write>1</vtx_write>
    <vtx_write>3</vtx_write>
  </node>
  <node>
    <id>15</id>
    <exec_a>20</exec_a>
    <exec_b>5</exec_b>
    <childs>9</childs>
    <vtx_read/>
    <vtx_write>3</vtx_write>
  </node>
  <node>
    <id>16</id>
    <exec_a>10</exec_a>
    <exec_b>7</exec_b>
    <childs>6</childs>
    <vtx_read/>
    <vtx_write>2</vtx_write>
  </node>
  <node>
    <id>17</id>
    <exec_a>20</exec_a>
    <exec_b>5</exec_b>
    <childs>18</childs>
    <vtx_read/>
    <vtx_write>5</vtx_write>
  </node>
  <node>
    <id>18</id>
    <exec_a>10</exec_a>
    <exec_b>7</exec_b>
    <childs>19</childs>
    <vtx_read/>
    <vtx_write>5</vtx_write>
  </node>
  <node>
    <id>19</id>
    <exec_a>30</exec_a>
    <exec_b>20</exec_b>
    <childs>19</childs>
    <childs>22</childs>
    <vtx_read>0</vtx_read>
    <vtx_read>5</vtx_read>
    <vtx_write/>
  </node>
  <node>
    <id>20</id>
    <exec_a>180</exec_a>
    <exec_b>110</exec_b>
    <childs>21</childs>
    <vtx_read>1</vtx_read>
    <vtx_read>5</vtx_read>
    <vtx_write/>
  </node>
  <node>
    <id>21</id>
    <exec_a>20</exec_a>
    <exec_b>5</exec_b>
    <childs>19</childs>
    <vtx_read/>
    <vtx_write>5</vtx_write>
  </node>
  <node>
    <id>22</id>
    <exec_a>0</exec_a>
    <exec_b>0</exec_b>
    <childs/>
    <vtx_read/>
    <vtx_write/>
  </node>
  <object>
    <id>0</id>
    <weight>4</weight>
  </object>
  <object>
    <id>1</id>
    <weight>20</weight>
  </object>
  <object>
    <id>2</id>
    <weight>4</weight>
  </object>
  <object>
    <id>3</id>
    <weight>4</weight>
  </object>
  <object>
    <id>4</id>
    <weight>4</weight>
  </object>
  <object>
    <id>5</id>
    <weight>4</weight>
  </object>
</root>